robotz/LogFile.py
robotz/RWLock.py
robotz/Scheduler.py
robotz/Subprocess.py
robotz/Version.py
robotz/__init__.py
robotz/barrier.py
robotz/core.py
robotz/dequeue.py
robotz/escrow.py
robotz/flag.py
robotz/gang.py
robotz/gate.py
robotz/processor.py
robotz/producer.py
robotz/promise.py
robotz/subprocess_3_11.py
robotz/task_queue.py
tests/chained_processors.py
tests/processor.py
tests/processor_async.py
tests/processors.py
tests/rwlock.py
tests/scheduler.py
tests/task_queue.py
tests/task_queue_stagger.py
tests/tasks_exceptions.py
robotz-2.16.0.dist-info/LICENSE
robotz-2.16.0.dist-info/METADATA
robotz-2.16.0.dist-info/WHEEL
robotz-2.16.0.dist-info/entry_points.txt
robotz-2.16.0.dist-info/top_level.txt
robotz-2.16.0.dist-info/RECORD
