Metadata-Version: 2.1
Name: robotz
Version: 2.16.0
Summary: A set of useful tools built on top of standard Python threading module
Home-page: https://github.com/imandr/robotz
Author: Igor Mandrichenko
Author-email: igorvm@gmail.com
License: BSD 3-clause
Keywords: threading,synchronization,multiprocessing,parallel computing
Classifier: Operating System :: POSIX
Classifier: Topic :: Software Development :: Libraries :: Python Modules
Classifier: Programming Language :: Python
Classifier: Topic :: Software Development :: Libraries
Classifier: Development Status :: 5 - Production/Stable
Classifier: Topic :: Utilities
Classifier: License :: OSI Approved :: BSD License
Classifier: Programming Language :: Python
Classifier: Programming Language :: Python :: 3
License-File: LICENSE
